MANIFEST.in
setup.py
boondoggle/__init__.py
boondoggle/cli.py
boondoggle/managers.py
boondoggle.egg-info/PKG-INFO
boondoggle.egg-info/SOURCES.txt
boondoggle.egg-info/dependency_links.txt
boondoggle.egg-info/entry_points.txt
boondoggle.egg-info/requires.txt
boondoggle.egg-info/top_level.txt