Metadata-Version: 1.1
Name: boondoggle
Version: 2.5
Summary: A script to deploy server fleets using pre-baked AMIs
Home-page: https://github.com/scopely-devops/boondoggle
Author: Scopely
Author-email: ops@scopely.com
License: UNKNOWN
Keywords: aws cli fleet ec2 ami
Platform: UNKNOWN
Classifier: Topic :: Utilities
